{"nodes":[{"id":"0","label":"fla2014","group":"0","value":"91.0"},{"id":"1","label":"liveon4g","group":"0","value":"21.0"},{"id":"2","label":"pescara","group":"0","value":"18.0"},{"id":"3","label":"anna masera","group":"0","value":"12.0"},{"id":"4","label":"pif","group":"0","value":"14.0"},{"id":"5","label":"abruzzo","group":"0","value":"4.0"},{"id":"6","label":"aldocazzullo","group":"0","value":"4.0"},{"id":"7","label":"luca sofri","group":"0","value":"10.0"},{"id":"8","label":"enrico mentana","group":"0","value":"7.0"},{"id":"9","label":"colibrìensemble","group":"0","value":"4.0"},{"id":"10","label":"enricomentana","group":"0","value":"3.0"},{"id":"11","label":"mariotozzi","group":"0","value":"3.0"},{"id":"12","label":"aldo cazzullo","group":"0","value":"3.0"},{"id":"13","label":"massimiliano panarari","group":"0","value":"5.0"},{"id":"14","label":"marino sinibaldi","group":"0","value":"3.0"},{"id":"15","label":"beppe severgnini","group":"0","value":"18.0"},{"id":"16","label":"mentana","group":"0","value":"2.0"},{"id":"17","label":"cosebelle","group":"0","value":"1.0"},{"id":"18","label":"livetweet","group":"0","value":"1.0"},{"id":"19","label":"domenicogalassi","group":"0","value":"1.0"},{"id":"20","label":"sapevatelo","group":"0","value":"1.0"},{"id":"21","label":"sonia peronaci","group":"0","value":"9.0"},{"id":"22","label":"invitro","group":"0","value":"1.0"},{"id":"23","label":"politica","group":"0","value":"1.0"},{"id":"24","label":"iostoconeuropa","group":"0","value":"2.0"},{"id":"25","label":"oroblu","group":"0","value":"1.0"},{"id":"26","label":"duomodimilano","group":"0","value":"1.0"},{"id":"27","label":"tuttiacasa","group":"0","value":"1.0"},{"id":"28","label":"iosonopartita","group":"0","value":"1.0"},{"id":"29","label":"berlinwall","group":"0","value":"1.0"},{"id":"30","label":"bersagliomobile","group":"0","value":"1.0"},{"id":"31","label":"pasticceria","group":"0","value":"1.0"},{"id":"32","label":"simonebaldasseronichef","group":"0","value":"1.0"},{"id":"33","label":"crowdfunding","group":"0","value":"1.0"},{"id":"34","label":"arianna ciccone","group":"0","value":"2.0"},{"id":"35","label":"livesocial","group":"0","value":"1.0"},{"id":"36","label":"festival delle letterature","group":"0","value":"1.0"},{"id":"37","label":"siamomedici","group":"0","value":"4.0"},{"id":"38","label":"labuonascuola","group":"0","value":"4.0"},{"id":"39","label":"12000borse","group":"0","value":"4.0"},{"id":"40","label":"petruzzi","group":"0","value":"1.0"},{"id":"41","label":"lapadania","group":"0","value":"2.0"},{"id":"42","label":"dario franceschini","group":"1","value":"48.0"},{"id":"43","label":"colosseo","group":"1","value":"7.0"},{"id":"44","label":"entula","group":"1","value":"6.0"},{"id":"45","label":"stileliberos","group":"1","value":"3.0"},{"id":"46","label":"chetempochefa","group":"1","value":"2.0"},{"id":"47","label":"massimo mantellini","group":"2","value":"11.0"},{"id":"48","label":"internet","group":"2","value":"3.0"},{"id":"49","label":"samuele bersani","group":"3","value":"3.0"},{"id":"50","label":"daria bignardi","group":"4","value":"2.0"},{"id":"51","label":"tozzi","group":"5","value":"2.0"},{"id":"52","label":"pietrangelo buttafuoco","group":"6","value":"1.0"},{"id":"53","label":"buttafuoco","group":"6","value":"1.0"},{"id":"54","label":"scarpestrette","group":"6","value":"1.0"},{"id":"55","label":"nosense","group":"7","value":"1.0"},{"id":"56","label":"preshow","group":"8","value":"1.0"},{"id":"57","label":"enricostaisereno","group":"9","value":"1.0"},{"id":"58","label":"venezia","group":"10","value":"1.0"},{"id":"59","label":"biennalearte","group":"10","value":"1.0"},{"id":"60","label":"glocal14","group":"11","value":"1.0"},{"id":"61","label":"genova","group":"12","value":"1.0"},{"id":"62","label":"instagram","group":"12","value":"1.0"},{"id":"63","label":"fulvio ervas","group":"12","value":"1.0"},{"id":"64","label":"liguria","group":"12","value":"1.0"},{"id":"65","label":"matera","group":"13","value":"1.0"},{"id":"66","label":"santamariadelpopolo","group":"14","value":"1.0"},{"id":"67","label":"angelsanddemons","group":"14","value":"1.0"},{"id":"68","label":"danbrown","group":"14","value":"1.0"},{"id":"69","label":"palestine","group":"15","value":"1.0"},{"id":"70","label":"laferocia","group":"16","value":"1.0"},{"id":"71","label":"news","group":"17","value":"1.0"},{"id":"72","label":"esquilino","group":"18","value":"1.0"},{"id":"73","label":"spendingreview","group":"18","value":"1.0"},{"id":"74","label":"roma","group":"18","value":"1.0"},{"id":"75","label":"mnao","group":"18","value":"1.0"}],"links":[{"source":0,"target":1,"value":0.7802197802197802},{"source":0,"target":2,"value":0.8021978021978022},{"source":0,"target":3,"value":0.8791208791208791},{"source":0,"target":4,"value":0.9120879120879121},{"source":0,"target":5,"value":0.9560439560439561},{"source":0,"target":6,"value":0.9560439560439561},{"source":0,"target":7,"value":0.9560439560439561},{"source":0,"target":8,"value":0.9560439560439561},{"source":0,"target":9,"value":0.9560439560439561},{"source":0,"target":10,"value":0.967032967032967},{"source":0,"target":11,"value":0.967032967032967},{"source":0,"target":12,"value":0.967032967032967},{"source":0,"target":13,"value":0.978021978021978},{"source":0,"target":14,"value":0.978021978021978},{"source":0,"target":15,"value":0.978021978021978},{"source":0,"target":16,"value":0.978021978021978},{"source":0,"target":17,"value":0.989010989010989},{"source":0,"target":18,"value":0.989010989010989},{"source":0,"target":19,"value":0.989010989010989},{"source":0,"target":20,"value":0.989010989010989},{"source":0,"target":21,"value":0.989010989010989},{"source":0,"target":22,"value":0.989010989010989},{"source":0,"target":23,"value":0.989010989010989},{"source":0,"target":24,"value":0.989010989010989},{"source":0,"target":25,"value":0.989010989010989},{"source":0,"target":26,"value":1.0},{"source":0,"target":27,"value":1.0},{"source":0,"target":28,"value":1.0},{"source":0,"target":29,"value":1.0},{"source":0,"target":30,"value":1.0},{"source":0,"target":31,"value":1.0},{"source":0,"target":32,"value":1.0},{"source":0,"target":33,"value":1.0},{"source":0,"target":34,"value":1.0},{"source":0,"target":35,"value":1.0},{"source":0,"target":36,"value":1.0},{"source":0,"target":37,"value":1.0},{"source":0,"target":38,"value":1.0},{"source":0,"target":39,"value":1.0},{"source":0,"target":40,"value":1.0},{"source":0,"target":41,"value":1.0},{"source":42,"target":43,"value":0.8541666666666666},{"source":42,"target":44,"value":0.875},{"source":42,"target":45,"value":0.9375},{"source":42,"target":46,"value":0.9583333333333334},{"source":47,"target":48,"value":0.7272727272727273},{"source":52,"target":53,"value":0.01},{"source":52,"target":54,"value":0.01},{"source":58,"target":59,"value":0.01},{"source":61,"target":62,"value":0.01},{"source":61,"target":63,"value":0.01},{"source":61,"target":64,"value":0.01},{"source":66,"target":67,"value":0.01},{"source":66,"target":68,"value":0.01},{"source":72,"target":73,"value":0.01},{"source":72,"target":74,"value":0.01},{"source":72,"target":75,"value":0.01},{"source":0,"target":51,"value":9.78021978021978},{"source":0,"target":55,"value":9.89010989010989},{"source":0,"target":56,"value":9.89010989010989},{"source":0,"target":71,"value":9.89010989010989},{"source":42,"target":57,"value":9.791666666666666},{"source":42,"target":58,"value":9.791666666666666},{"source":42,"target":65,"value":9.791666666666666},{"source":42,"target":66,"value":9.791666666666666},{"source":42,"target":69,"value":9.791666666666666},{"source":42,"target":72,"value":9.791666666666666}]}
