{"nodes":[{"id":"0","label":"dario franceschini","group":"0","value":"491.0"},{"id":"1","label":"chetempochefa","group":"0","value":"156.0"},{"id":"2","label":"cultura","group":"0","value":"44.0"},{"id":"3","label":"unlibroèunlibro","group":"0","value":"22.0"},{"id":"4","label":"pompei","group":"0","value":"15.0"},{"id":"5","label":"colosseo","group":"0","value":"13.0"},{"id":"6","label":"matera","group":"0","value":"10.0"},{"id":"7","label":"salviamopompei","group":"0","value":"7.0"},{"id":"8","label":"ecoc2019","group":"0","value":"6.0"},{"id":"9","label":"governorenzi","group":"0","value":"6.0"},{"id":"10","label":"franceschini","group":"0","value":"6.0"},{"id":"11","label":"libri","group":"0","value":"5.0"},{"id":"12","label":"ministro","group":"0","value":"4.0"},{"id":"13","label":"turismo","group":"0","value":"4.0"},{"id":"14","label":"italy","group":"0","value":"3.0"},{"id":"15","label":"concerts","group":"0","value":"3.0"},{"id":"16","label":"ebook","group":"0","value":"3.0"},{"id":"17","label":"iva","group":"0","value":"2.0"},{"id":"18","label":"rai3","group":"0","value":"2.0"},{"id":"19","label":"regionecampania","group":"0","value":"2.0"},{"id":"20","label":"nocomment","group":"0","value":"2.0"},{"id":"21","label":"unlibroèunlbro","group":"0","value":"2.0"},{"id":"22","label":"suora","group":"0","value":"2.0"},{"id":"23","label":"fabiofazio","group":"0","value":"2.0"},{"id":"24","label":"sassi","group":"0","value":"1.0"},{"id":"25","label":"senzafiltri","group":"0","value":"1.0"},{"id":"26","label":"beniculturali","group":"0","value":"1.0"},{"id":"27","label":"blasfemo","group":"0","value":"1.0"},{"id":"28","label":"churcill","group":"0","value":"1.0"},{"id":"29","label":"scuola","group":"0","value":"1.0"},{"id":"30","label":"piùtwittati","group":"0","value":"1.0"},{"id":"31","label":"bellenotizie","group":"0","value":"7.0"},{"id":"32","label":"mipiace","group":"0","value":"1.0"},{"id":"33","label":"wtm","group":"0","value":"1.0"},{"id":"34","label":"libro","group":"0","value":"1.0"},{"id":"35","label":"fla2014","group":"1","value":"59.0"},{"id":"36","label":"liveon4g","group":"1","value":"31.0"},{"id":"37","label":"pif","group":"1","value":"24.0"},{"id":"38","label":"luca sofri","group":"1","value":"12.0"},{"id":"39","label":"marino sinibaldi","group":"1","value":"7.0"},{"id":"40","label":"sonia peronaci","group":"1","value":"6.0"},{"id":"41","label":"samuele bersani","group":"1","value":"10.0"},{"id":"42","label":"media","group":"1","value":"3.0"},{"id":"43","label":"app","group":"1","value":"3.0"},{"id":"44","label":"food","group":"1","value":"3.0"},{"id":"45","label":"beppe severgnini","group":"1","value":"12.0"},{"id":"46","label":"bersani","group":"1","value":"2.0"},{"id":"47","label":"lucasofri","group":"1","value":"1.0"},{"id":"48","label":"siamoaltop","group":"1","value":"1.0"},{"id":"49","label":"marinosinibaldi","group":"1","value":"1.0"},{"id":"50","label":"festival delle letterature","group":"1","value":"2.0"},{"id":"51","label":"unmillemetroinla","group":"1","value":"1.0"},{"id":"52","label":"jolskil","group":"1","value":"1.0"},{"id":"53","label":"natale","group":"1","value":"1.0"},{"id":"54","label":"scoprimi","group":"1","value":"1.0"},{"id":"55","label":"christmas","group":"1","value":"1.0"},{"id":"56","label":"shazam","group":"1","value":"1.0"},{"id":"57","label":"europa","group":"1","value":"5.0"},{"id":"58","label":"goofy3","group":"1","value":"2.0"},{"id":"59","label":"mafia","group":"1","value":"5.0"},{"id":"60","label":"milano","group":"1","value":"5.0"},{"id":"61","label":"massimo mantellini","group":"2","value":"37.0"},{"id":"62","label":"unlibroeunlibro","group":"3","value":"10.0"},{"id":"63","label":"matera2019","group":"4","value":"4.0"},{"id":"64","label":"arianna ciccone","group":"5","value":"3.0"},{"id":"65","label":"anna masera","group":"6","value":"3.0"},{"id":"66","label":"fazio","group":"7","value":"2.0"},{"id":"67","label":"magazzino18intv","group":"8","value":"2.0"},{"id":"68","label":"sud","group":"9","value":"6.0"},{"id":"69","label":"cameredicommercio","group":"10","value":"2.0"},{"id":"70","label":"isognisondesideri","group":"11","value":"5.0"},{"id":"71","label":"ahlitalia","group":"11","value":"4.0"},{"id":"72","label":"musicisti","group":"12","value":"2.0"},{"id":"73","label":"massimobray","group":"13","value":"2.0"},{"id":"74","label":"santommaso","group":"14","value":"1.0"},{"id":"75","label":"bbcc","group":"15","value":"1.0"},{"id":"76","label":"soprintendenze","group":"16","value":"1.0"},{"id":"77","label":"mtvema","group":"17","value":"1.0"},{"id":"78","label":"sapevatelo","group":"18","value":"1.0"},{"id":"79","label":"daje","group":"19","value":"1.0"},{"id":"80","label":"pescara","group":"20","value":"1.0"},{"id":"81","label":"tempo","group":"21","value":"1.0"},{"id":"82","label":"fa","group":"21","value":"1.0"},{"id":"83","label":"turismosostenibile","group":"22","value":"1.0"},{"id":"84","label":"spal","group":"23","value":"1.0"},{"id":"85","label":"pd","group":"24","value":"1.0"},{"id":"86","label":"zaccagnini","group":"24","value":"1.0"},{"id":"87","label":"italia","group":"25","value":"1.0"},{"id":"88","label":"londra","group":"25","value":"1.0"},{"id":"89","label":"magari","group":"26","value":"1.0"},{"id":"90","label":"residenzeborboniche","group":"27","value":"1.0"},{"id":"91","label":"percosacombattiamo","group":"28","value":"1.0"},{"id":"92","label":"live","group":"29","value":"1.0"},{"id":"93","label":"suorcristina","group":"30","value":"1.0"},{"id":"94","label":"sicambia","group":"31","value":"1.0"},{"id":"95","label":"italialand","group":"32","value":"1.0"},{"id":"96","label":"gufi","group":"33","value":"1.0"},{"id":"97","label":"sviluppo","group":"34","value":"1.0"},{"id":"98","label":"futuro","group":"34","value":"1.0"}],"links":[{"source":0,"target":1,"value":0.6945010183299389},{"source":0,"target":2,"value":0.9103869653767821},{"source":0,"target":3,"value":0.955193482688391},{"source":0,"target":4,"value":0.9694501018329938},{"source":0,"target":5,"value":0.9735234215885947},{"source":0,"target":6,"value":0.9796334012219959},{"source":0,"target":7,"value":0.9857433808553971},{"source":0,"target":8,"value":0.9877800407331976},{"source":0,"target":9,"value":0.9877800407331976},{"source":0,"target":10,"value":0.9877800407331976},{"source":0,"target":11,"value":0.9898167006109979},{"source":0,"target":12,"value":0.9918533604887984},{"source":0,"target":13,"value":0.9918533604887984},{"source":0,"target":14,"value":0.9938900203665988},{"source":0,"target":15,"value":0.9938900203665988},{"source":0,"target":16,"value":0.9938900203665988},{"source":0,"target":17,"value":0.9959266802443992},{"source":0,"target":18,"value":0.9959266802443992},{"source":0,"target":19,"value":0.9959266802443992},{"source":0,"target":20,"value":0.9959266802443992},{"source":0,"target":21,"value":0.9959266802443992},{"source":0,"target":22,"value":0.9959266802443992},{"source":0,"target":23,"value":0.9959266802443992},{"source":0,"target":24,"value":0.9979633401221996},{"source":0,"target":25,"value":0.9979633401221996},{"source":0,"target":26,"value":0.9979633401221996},{"source":0,"target":27,"value":0.9979633401221996},{"source":0,"target":28,"value":0.9979633401221996},{"source":0,"target":29,"value":0.9979633401221996},{"source":0,"target":30,"value":0.9979633401221996},{"source":0,"target":31,"value":0.9979633401221996},{"source":0,"target":32,"value":0.9979633401221996},{"source":0,"target":33,"value":0.9979633401221996},{"source":0,"target":34,"value":0.9979633401221996},{"source":35,"target":36,"value":0.4915254237288136},{"source":35,"target":37,"value":0.8135593220338984},{"source":35,"target":38,"value":0.8983050847457628},{"source":35,"target":39,"value":0.8983050847457628},{"source":35,"target":40,"value":0.9152542372881356},{"source":35,"target":41,"value":0.9491525423728814},{"source":35,"target":42,"value":0.9491525423728814},{"source":35,"target":43,"value":0.9491525423728814},{"source":35,"target":44,"value":0.9491525423728814},{"source":35,"target":45,"value":0.9661016949152542},{"source":35,"target":46,"value":0.9661016949152542},{"source":35,"target":47,"value":0.9830508474576272},{"source":35,"target":48,"value":0.9830508474576272},{"source":35,"target":49,"value":0.9830508474576272},{"source":35,"target":50,"value":0.9830508474576272},{"source":35,"target":51,"value":0.9830508474576272},{"source":35,"target":52,"value":0.9830508474576272},{"source":35,"target":53,"value":1.0},{"source":35,"target":54,"value":1.0},{"source":35,"target":55,"value":1.0},{"source":35,"target":56,"value":1.0},{"source":35,"target":57,"value":1.0},{"source":35,"target":58,"value":1.0},{"source":35,"target":59,"value":1.0},{"source":35,"target":60,"value":1.0},{"source":70,"target":71,"value":0.19999999999999996},{"source":81,"target":82,"value":0.01},{"source":85,"target":86,"value":0.01},{"source":87,"target":88,"value":0.01},{"source":97,"target":98,"value":0.01},{"source":0,"target":62,"value":9.79633401221996},{"source":0,"target":63,"value":9.918533604887983},{"source":0,"target":66,"value":9.959266802443992},{"source":0,"target":67,"value":9.959266802443992},{"source":0,"target":68,"value":9.877800407331975},{"source":0,"target":69,"value":9.979633401221996},{"source":0,"target":70,"value":9.89816700610998},{"source":0,"target":72,"value":9.959266802443992},{"source":0,"target":73,"value":9.959266802443992},{"source":0,"target":74,"value":9.979633401221996},{"source":0,"target":75,"value":9.979633401221996},{"source":0,"target":76,"value":9.979633401221996},{"source":0,"target":78,"value":9.979633401221996},{"source":0,"target":79,"value":9.979633401221996},{"source":35,"target":65,"value":9.830508474576272},{"source":61,"target":77,"value":9.72972972972973}]}
