{"nodes":[{"id":"0","label":"dario franceschini","group":"0","value":"22.0"},{"id":"1","label":"incrocialebraccia","group":"0","value":"12.0"},{"id":"2","label":"colosseo","group":"0","value":"1.0"},{"id":"3","label":"menotassepiuerogazioni","group":"0","value":"1.0"},{"id":"4","label":"nunsepòsentì","group":"0","value":"1.0"},{"id":"5","label":"sassi","group":"0","value":"1.0"},{"id":"6","label":"balneari","group":"0","value":"1.0"},{"id":"7","label":"bolkestein","group":"0","value":"1.0"},{"id":"8","label":"salviamoilteatro","group":"0","value":"1.0"},{"id":"9","label":"kaulon","group":"0","value":"1.0"},{"id":"10","label":"teatro","group":"0","value":"1.0"},{"id":"11","label":"fondazioni","group":"0","value":"1.0"},{"id":"12","label":"daria bignardi","group":"0","value":"2.0"},{"id":"13","label":"senzacontraddittorio","group":"0","value":"1.0"},{"id":"14","label":"mtvitaly","group":"0","value":"1.0"},{"id":"15","label":"announo","group":"0","value":"2.0"},{"id":"16","label":"dimario","group":"0","value":"2.0"},{"id":"17","label":"soro","group":"0","value":"2.0"},{"id":"18","label":"cocacola","group":"0","value":"1.0"},{"id":"19","label":"pizza","group":"0","value":"1.0"},{"id":"20","label":"convegnoprivacy","group":"0","value":"1.0"},{"id":"21","label":"staiconpif","group":"0","value":"1.0"},{"id":"22","label":"marino sinibaldi","group":"0","value":"1.0"},{"id":"23","label":"roma","group":"0","value":"1.0"},{"id":"24","label":"internet","group":"0","value":"2.0"},{"id":"25","label":"billofrights","group":"0","value":"4.0"},{"id":"26","label":"pisa","group":"0","value":"2.0"},{"id":"27","label":"pif","group":"0","value":"11.0"},{"id":"28","label":"giustiziaperlele","group":"0","value":"2.0"},{"id":"29","label":"sicilia","group":"0","value":"2.0"},{"id":"30","label":"governanceinternetprivacy","group":"0","value":"2.0"},{"id":"31","label":"rodotà","group":"0","value":"3.0"},{"id":"32","label":"anna masera","group":"0","value":"10.0"},{"id":"33","label":"massimo mantellini","group":"1","value":"23.0"},{"id":"34","label":"xfactor2014","group":"1","value":"1.0"},{"id":"35","label":"luca sofri","group":"2","value":"15.0"},{"id":"36","label":"sit14","group":"2","value":"1.0"},{"id":"37","label":"beppe severgnini","group":"3","value":"11.0"},{"id":"38","label":"twitterbullismo","group":"3","value":"3.0"},{"id":"39","label":"sfigato","group":"3","value":"3.0"},{"id":"40","label":"bologna","group":"3","value":"1.0"},{"id":"41","label":"news","group":"3","value":"1.0"},{"id":"42","label":"sonia peronaci","group":"4","value":"11.0"},{"id":"43","label":"bookcity","group":"4","value":"3.0"},{"id":"44","label":"mondadori","group":"4","value":"3.0"},{"id":"45","label":"bookcitymilano","group":"4","value":"3.0"},{"id":"46","label":"arianna ciccone","group":"5","value":"4.0"},{"id":"47","label":"silvia ballestra","group":"6","value":"3.0"},{"id":"48","label":"samuele bersani","group":"7","value":"2.0"},{"id":"49","label":"festival delle letterature","group":"7","value":"1.0"},{"id":"50","label":"aldo cazzullo","group":"8","value":"1.0"},{"id":"51","label":"grandeguerra","group":"8","value":"1.0"},{"id":"52","label":"padova","group":"8","value":"1.0"},{"id":"53","label":"teatroverdi","group":"8","value":"1.0"},{"id":"54","label":"bcm14","group":"9","value":"1.0"},{"id":"55","label":"enrico mentana","group":"10","value":"1.0"},{"id":"56","label":"mentana","group":"10","value":"1.0"},{"id":"57","label":"tg7","group":"10","value":"1.0"},{"id":"58","label":"pietrangelo buttafuoco","group":"11","value":"2.0"},{"id":"59","label":"articolo18","group":"12","value":"2.0"},{"id":"60","label":"ritiriamoladelibera","group":"13","value":"2.0"},{"id":"61","label":"stage","group":"14","value":"1.0"},{"id":"62","label":"gentiloni","group":"14","value":"1.0"},{"id":"63","label":"backtoitaly","group":"15","value":"1.0"},{"id":"64","label":"convegnopambianco14","group":"15","value":"1.0"},{"id":"65","label":"torsperanza","group":"16","value":"1.0"},{"id":"66","label":"speranza","group":"16","value":"1.0"},{"id":"67","label":"torsapienza","group":"16","value":"1.0"},{"id":"68","label":"tgla7","group":"16","value":"1.0"},{"id":"69","label":"cameraconvision","group":"17","value":"3.0"},{"id":"70","label":"turismo","group":"17","value":"3.0"},{"id":"71","label":"montecitorio","group":"17","value":"3.0"}],"links":[{"source":0,"target":1,"value":0.6818181818181819},{"source":0,"target":2,"value":0.9545454545454546},{"source":0,"target":3,"value":0.9545454545454546},{"source":0,"target":4,"value":0.9545454545454546},{"source":0,"target":5,"value":0.9545454545454546},{"source":0,"target":6,"value":0.9545454545454546},{"source":0,"target":7,"value":0.9545454545454546},{"source":0,"target":8,"value":0.9545454545454546},{"source":0,"target":9,"value":0.9545454545454546},{"source":0,"target":10,"value":0.9545454545454546},{"source":0,"target":11,"value":0.9545454545454546},{"source":0,"target":12,"value":1.0},{"source":0,"target":13,"value":1.0},{"source":0,"target":14,"value":1.0},{"source":0,"target":15,"value":1.0},{"source":0,"target":16,"value":1.0},{"source":0,"target":17,"value":1.0},{"source":0,"target":18,"value":1.0},{"source":0,"target":19,"value":1.0},{"source":0,"target":20,"value":1.0},{"source":0,"target":21,"value":1.0},{"source":0,"target":22,"value":1.0},{"source":0,"target":23,"value":1.0},{"source":0,"target":24,"value":1.0},{"source":0,"target":25,"value":1.0},{"source":0,"target":26,"value":1.0},{"source":0,"target":27,"value":1.0},{"source":0,"target":28,"value":1.0},{"source":0,"target":29,"value":1.0},{"source":0,"target":30,"value":1.0},{"source":0,"target":31,"value":1.0},{"source":0,"target":32,"value":1.0},{"source":33,"target":34,"value":0.9565217391304348},{"source":35,"target":36,"value":0.9333333333333333},{"source":37,"target":38,"value":0.7272727272727273},{"source":37,"target":39,"value":0.7272727272727273},{"source":37,"target":40,"value":0.9090909090909091},{"source":37,"target":41,"value":0.9090909090909091},{"source":42,"target":43,"value":0.7272727272727273},{"source":42,"target":44,"value":0.7272727272727273},{"source":42,"target":45,"value":0.7272727272727273},{"source":48,"target":49,"value":0.5},{"source":50,"target":51,"value":0.01},{"source":50,"target":52,"value":0.01},{"source":50,"target":53,"value":0.01},{"source":55,"target":56,"value":0.01},{"source":55,"target":57,"value":0.01},{"source":61,"target":62,"value":0.01},{"source":63,"target":64,"value":0.01},{"source":65,"target":66,"value":0.01},{"source":65,"target":67,"value":0.01},{"source":65,"target":68,"value":0.01},{"source":69,"target":70,"value":0.01},{"source":69,"target":71,"value":0.01}]}
