{"nodes":[{"id":"0","label":"anna masera","group":"0","value":"19.0"},{"id":"1","label":"rodotà","group":"0","value":"14.0"},{"id":"2","label":"convegnoprivacy","group":"0","value":"11.0"},{"id":"3","label":"roma","group":"0","value":"11.0"},{"id":"4","label":"dimario","group":"0","value":"3.0"},{"id":"5","label":"soro","group":"0","value":"3.0"},{"id":"6","label":"governanceinternetprivacy","group":"0","value":"3.0"},{"id":"7","label":"saythanks","group":"0","value":"1.0"},{"id":"8","label":"madeinitaly","group":"0","value":"1.0"},{"id":"9","label":"eccedigit","group":"0","value":"1.0"},{"id":"10","label":"montecitorio","group":"0","value":"5.0"},{"id":"11","label":"turismo","group":"0","value":"6.0"},{"id":"12","label":"cameraconvision","group":"0","value":"5.0"},{"id":"13","label":"cameredicommercio","group":"0","value":"1.0"},{"id":"14","label":"colosseo","group":"0","value":"1.0"},{"id":"15","label":"salonerestaurofi14","group":"0","value":"2.0"},{"id":"16","label":"diveintocriticism","group":"0","value":"1.0"},{"id":"17","label":"next2014","group":"0","value":"1.0"},{"id":"18","label":"daidario","group":"0","value":"1.0"},{"id":"19","label":"dario franceschini","group":"0","value":"13.0"},{"id":"20","label":"luca sofri","group":"1","value":"20.0"},{"id":"21","label":"ireland2016","group":"1","value":"1.0"},{"id":"22","label":"irlanda","group":"1","value":"1.0"},{"id":"23","label":"bono","group":"1","value":"1.0"},{"id":"24","label":"sit14","group":"1","value":"1.0"},{"id":"25","label":"beppe severgnini","group":"2","value":"10.0"},{"id":"26","label":"ue","group":"2","value":"1.0"},{"id":"27","label":"news","group":"2","value":"1.0"},{"id":"28","label":"bsev","group":"2","value":"1.0"},{"id":"29","label":"eupol","group":"2","value":"1.0"},{"id":"30","label":"vignola","group":"2","value":"1.0"},{"id":"31","label":"bologna","group":"2","value":"1.0"},{"id":"32","label":"massimo mantellini","group":"3","value":"6.0"},{"id":"33","label":"cucchi","group":"3","value":"2.0"},{"id":"34","label":"arianna ciccone","group":"4","value":"6.0"},{"id":"35","label":"pietrangelo buttafuoco","group":"5","value":"5.0"},{"id":"36","label":"lacameragrassa","group":"5","value":"1.0"},{"id":"37","label":"sonia peronaci","group":"6","value":"4.0"},{"id":"38","label":"ford","group":"6","value":"3.0"},{"id":"39","label":"siena","group":"6","value":"2.0"},{"id":"40","label":"ecosport","group":"6","value":"2.0"},{"id":"41","label":"tasteontheroad","group":"6","value":"2.0"},{"id":"42","label":"giallozafferano","group":"6","value":"1.0"},{"id":"43","label":"gialloblogs","group":"6","value":"1.0"},{"id":"44","label":"soniaperonaci","group":"6","value":"1.0"},{"id":"45","label":"samuele bersani","group":"7","value":"3.0"},{"id":"46","label":"recensioni","group":"8","value":"2.0"},{"id":"47","label":"romanzocontemporaneo","group":"8","value":"2.0"},{"id":"48","label":"daria bignardi","group":"9","value":"2.0"},{"id":"49","label":"giornidispasimatoamore","group":"10","value":"2.0"},{"id":"50","label":"romana petri","group":"10","value":"2.0"},{"id":"51","label":"romanzo","group":"11","value":"1.0"},{"id":"52","label":"recensione","group":"11","value":"1.0"},{"id":"53","label":"fulvio ervas","group":"12","value":"1.0"},{"id":"54","label":"festival delle letterature","group":"13","value":"1.0"},{"id":"55","label":"francesco","group":"14","value":"1.0"},{"id":"56","label":"facchinetti","group":"14","value":"1.0"},{"id":"57","label":"progettolegalita14","group":"15","value":"1.0"},{"id":"58","label":"dallachiesa","group":"15","value":"1.0"},{"id":"59","label":"pif","group":"15","value":"1.0"},{"id":"60","label":"andreotti","group":"15","value":"1.0"}],"links":[{"source":0,"target":1,"value":0.26315789473684215},{"source":0,"target":2,"value":0.42105263157894735},{"source":0,"target":3,"value":0.42105263157894735},{"source":0,"target":4,"value":0.8421052631578947},{"source":0,"target":5,"value":0.8421052631578947},{"source":0,"target":6,"value":0.8421052631578947},{"source":0,"target":7,"value":0.9473684210526316},{"source":0,"target":8,"value":0.9473684210526316},{"source":0,"target":9,"value":0.9473684210526316},{"source":0,"target":10,"value":0.9473684210526316},{"source":0,"target":11,"value":0.9473684210526316},{"source":0,"target":12,"value":0.9473684210526316},{"source":0,"target":13,"value":0.9473684210526316},{"source":0,"target":14,"value":1.0},{"source":0,"target":15,"value":1.0},{"source":0,"target":16,"value":1.0},{"source":0,"target":17,"value":1.0},{"source":0,"target":18,"value":1.0},{"source":0,"target":19,"value":1.0},{"source":20,"target":21,"value":0.95},{"source":20,"target":22,"value":0.95},{"source":20,"target":23,"value":0.95},{"source":20,"target":24,"value":0.95},{"source":25,"target":26,"value":0.9},{"source":25,"target":27,"value":0.9},{"source":25,"target":28,"value":0.9},{"source":25,"target":29,"value":0.9},{"source":25,"target":30,"value":0.9},{"source":25,"target":31,"value":0.9},{"source":32,"target":33,"value":0.6666666666666667},{"source":35,"target":36,"value":0.8},{"source":37,"target":38,"value":0.25},{"source":37,"target":39,"value":0.5},{"source":37,"target":40,"value":0.5},{"source":37,"target":41,"value":0.5},{"source":37,"target":42,"value":0.75},{"source":37,"target":43,"value":0.75},{"source":37,"target":44,"value":0.75},{"source":46,"target":47,"value":0.01},{"source":49,"target":50,"value":0.01},{"source":51,"target":52,"value":0.01},{"source":55,"target":56,"value":0.01},{"source":57,"target":58,"value":0.01},{"source":57,"target":59,"value":0.01},{"source":57,"target":60,"value":0.01}]}
