{"nodes":[{"id":"0","label":"massimo mantellini","group":"0","value":"10.0"},{"id":"1","label":"anna masera","group":"0","value":"9.0"},{"id":"2","label":"socialmedia","group":"0","value":"3.0"},{"id":"3","label":"igf2014","group":"0","value":"1.0"},{"id":"4","label":"igf","group":"0","value":"1.0"},{"id":"5","label":"glocal14","group":"0","value":"5.0"},{"id":"6","label":"dario franceschini","group":"1","value":"14.0"},{"id":"7","label":"stabilità2015","group":"1","value":"5.0"},{"id":"8","label":"reggiadivenaria","group":"1","value":"1.0"},{"id":"9","label":"basilicata","group":"1","value":"1.0"},{"id":"10","label":"matera","group":"1","value":"1.0"},{"id":"11","label":"testasfinge","group":"1","value":"1.0"},{"id":"12","label":"beppe severgnini","group":"2","value":"11.0"},{"id":"13","label":"12000borse","group":"2","value":"1.0"},{"id":"14","label":"gianninidimettiti","group":"2","value":"1.0"},{"id":"15","label":"marino sinibaldi","group":"3","value":"3.0"},{"id":"16","label":"sapere","group":"3","value":"1.0"},{"id":"17","label":"elbareport","group":"3","value":"1.0"},{"id":"18","label":"cultura","group":"3","value":"1.0"},{"id":"19","label":"condivisione","group":"3","value":"1.0"},{"id":"20","label":"elbadipaul","group":"3","value":"1.0"},{"id":"21","label":"daria bignardi","group":"4","value":"1.0"},{"id":"22","label":"sonia peronaci","group":"5","value":"1.0"},{"id":"23","label":"mifacciodicultura","group":"6","value":"1.0"},{"id":"24","label":"aldo cazzullo","group":"6","value":"1.0"},{"id":"25","label":"soundhound","group":"7","value":"1.0"},{"id":"26","label":"samuele bersani","group":"7","value":"1.0"},{"id":"27","label":"massimiliano panarari","group":"8","value":"1.0"},{"id":"28","label":"themafiaonlykillsinsummer","group":"9","value":"1.0"},{"id":"29","label":"pif","group":"9","value":"1.0"},{"id":"30","label":"losangeles","group":"9","value":"1.0"},{"id":"31","label":"aerotheatre","group":"9","value":"1.0"},{"id":"32","label":"santamonica","group":"9","value":"1.0"}],"links":[{"source":0,"target":1,"value":0.8},{"source":0,"target":2,"value":1.0},{"source":0,"target":3,"value":1.0},{"source":0,"target":4,"value":1.0},{"source":0,"target":5,"value":1.0},{"source":6,"target":7,"value":0.6428571428571428},{"source":6,"target":8,"value":0.9285714285714286},{"source":6,"target":9,"value":0.9285714285714286},{"source":6,"target":10,"value":0.9285714285714286},{"source":6,"target":11,"value":0.9285714285714286},{"source":12,"target":13,"value":0.9090909090909091},{"source":12,"target":14,"value":0.9090909090909091},{"source":15,"target":16,"value":0.6666666666666667},{"source":15,"target":17,"value":0.6666666666666667},{"source":15,"target":18,"value":0.6666666666666667},{"source":15,"target":19,"value":0.6666666666666667},{"source":15,"target":20,"value":0.6666666666666667},{"source":23,"target":24,"value":0.01},{"source":25,"target":26,"value":0.01},{"source":28,"target":29,"value":0.01},{"source":28,"target":30,"value":0.01},{"source":28,"target":31,"value":0.01},{"source":28,"target":32,"value":0.01}]}
